spiderscan/__init__.py
spiderscan/cli.py
spiderscan/nvdRequests.py
spiderscan/vulnerabilityScanner.py
spiderscan-0.2.0.dist-info/licenses/LICENSE
spiderscan-0.2.0.dist-info/METADATA
spiderscan-0.2.0.dist-info/WHEEL
spiderscan-0.2.0.dist-info/entry_points.txt
spiderscan-0.2.0.dist-info/top_level.txt
spiderscan-0.2.0.dist-info/RECORD
