Metadata-Version: 2.4
Name: spiderscan
Version: 0.2.0
Summary: Asynchronous web vulnerability scanner
Author: Spencer Harman
Requires-Python: >=3.8
License-File: LICENSE
Requires-Dist: httpx
Requires-Dist: beautifulsoup4
Dynamic: license-file
